emilrex/__init__.py
emilrex/cli.py
emilrex-0.1.0.dist-info/LICENSE
emilrex-0.1.0.dist-info/METADATA
emilrex-0.1.0.dist-info/WHEEL
emilrex-0.1.0.dist-info/entry_points.txt
emilrex-0.1.0.dist-info/top_level.txt
emilrex-0.1.0.dist-info/RECORD
