Metadata-Version: 2.1
Name: emilrex
Version: 0.1.0
Summary: Personal Python package
Home-page: https://github.com/EmilRex/emilrex-py
Author: Emil Christensen
Author-email: emil.rex.christensen@gmail.com
Project-URL: Changelog, https://github.com/EmilRex/emilrex-py/blob/main/CHANGELOG.md
Project-URL: Source, https://github.com/EmilRex/emilrex-py
Project-URL: Tracker, https://github.com/EmilRex/emilrex-py/issues
Classifier: License :: OSI Approved :: MIT License
Classifier: Natural Language :: English
Classifier: Programming Language :: Python :: 3 :: Only
Requires-Python: >=3.7
License-File: LICENSE
Requires-Dist: typer
Provides-Extra: dev
Requires-Dist: black ; extra == 'dev'
